[
  {
    "slug": "ra-treat-to-target",
    "titleHe": "RA בגישת Treat-to-Target",
    "titleEn": "RA and the Treat-to-Target Approach",
    "summaryHe": "סקירה קצרה על חשיבות מעקב תדיר והגעה להפוגה או פעילות מחלה נמוכה.",
    "summaryEn": "A brief review on frequent follow-up and aiming for remission or low disease activity.",
    "checkedHe": "הוגדרו מדדי פעילות מחלה בביקורות חוזרות.",
    "checkedEn": "Disease activity measures were defined in repeated visits.",
    "insightHe": "התאמת טיפול מוקדמת משפרת תוצאות ארוכות טווח.",
    "insightEn": "Early treatment adjustment improves long-term outcomes.",
    "date": "2025-11-10",
    "tags": ["RA", "דלקת מפרקים"],
    "externalLink": "https://pubmed.ncbi.nlm.nih.gov/",
    "sourceName": "PubMed"
  },
  {
    "slug": "sle-monitoring",
    "titleHe": "מעקב חכם בלופוס",
    "titleEn": "Smart Monitoring in SLE",
    "summaryHe": "איזון בין פעילות מחלה למניעת תופעות לוואי, עם דגש על ניטור קבוע.",
    "summaryEn": "Balancing disease control with safety through structured monitoring.",
    "checkedHe": "נבדקו מדדי מעבדה מרכזיים ומעורבות איברים.",
    "checkedEn": "Key labs and organ involvement were reviewed.",
    "insightHe": "מעקב רציף מאפשר זיהוי מוקדם של התלקחויות.",
    "insightEn": "Consistent follow-up enables earlier flare detection.",
    "date": "2025-09-22",
    "tags": ["SLE", "לופוס"],
    "externalLink": "https://pubmed.ncbi.nlm.nih.gov/",
    "sourceName": "PubMed"
  },
  {
    "slug": "gout-urate-goals",
    "titleHe": "שיגדון: יעד חומצת שתן",
    "titleEn": "Gout: Uric Acid Targets",
    "summaryHe": "למה חשוב להגיע ליעד חומצת שתן ולשמור עליו למניעת התקפים.",
    "summaryEn": "Why reaching and maintaining uric acid targets prevents recurrent flares.",
    "checkedHe": "נבדקו רמות חומצת שתן ותדירות התקפים.",
    "checkedEn": "Uric acid levels and flare frequency were assessed.",
    "insightHe": "עמידה ביעד מפחיתה התקפים ומגנה על המפרק.",
    "insightEn": "Meeting target levels reduces flares and protects joints.",
    "date": "2025-07-14",
    "tags": ["Gout", "שיגדון"],
    "externalLink": "https://pubmed.ncbi.nlm.nih.gov/",
    "sourceName": "PubMed"
  },
  {
    "slug": "fmf-followup",
    "titleHe": "FMF: עקרונות מעקב",
    "titleEn": "FMF: Follow-up Principles",
    "summaryHe": "עקרונות מעקב בחולי FMF לשמירה על יציבות ומניעת סיבוכים.",
    "summaryEn": "Follow-up principles in FMF to maintain stability and prevent complications.",
    "checkedHe": "נבדקו תדירות התקפים, היענות לטיפול וסימני סיכון.",
    "checkedEn": "Flare frequency, adherence and risk markers were reviewed.",
    "insightHe": "תוכנית מעקב סדורה משפרת שליטה במחלה.",
    "insightEn": "A structured follow-up plan improves disease control.",
    "date": "2025-05-03",
    "tags": ["FMF", "אוטואימוני"],
    "externalLink": "https://pubmed.ncbi.nlm.nih.gov/",
    "sourceName": "PubMed"
  },
  {
    "slug": "vasculitis-red-flags",
    "titleHe": "וסקוליטיס: סימנים שדורשים בירור",
    "titleEn": "Vasculitis: Red Flags That Need Workup",
    "summaryHe": "סימנים קליניים ומעבדתיים המחייבים הערכה מהירה.",
    "summaryEn": "Clinical and laboratory signs that should trigger urgent assessment.",
    "checkedHe": "נסקרו תסמינים סיסטמיים וממצאי מעבדה.",
    "checkedEn": "Systemic symptoms and laboratory findings were reviewed.",
    "insightHe": "אבחון מוקדם מאפשר טיפול מדויק יותר.",
    "insightEn": "Early diagnosis enables more precise treatment.",
    "date": "2025-03-19",
    "tags": ["Vasculitis", "וסקוליטיס"],
    "externalLink": "https://pubmed.ncbi.nlm.nih.gov/",
    "sourceName": "PubMed"
  },
  {
    "slug": "spondylitis-early-diagnosis",
    "titleHe": "אבחון מוקדם בדלקת חוליות",
    "titleEn": "Early Diagnosis in Ankylosing Spondylitis",
    "summaryHe": "איך לזהות כאב גב דלקתי ולהפנות בזמן לריאומטולוג.",
    "summaryEn": "How to recognize inflammatory back pain and refer early to rheumatology.",
    "checkedHe": "נבדקו מאפייני כאב, הדמיה ותגובה לטיפול.",
    "checkedEn": "Pain pattern, imaging and treatment response were examined.",
    "insightHe": "הפניה מוקדמת מקצרת זמן עד טיפול יעיל.",
    "insightEn": "Early referral shortens time to effective care.",
    "date": "2025-01-28",
    "tags": ["Ankylosing Spondylitis", "דלקת חוליות"],
    "externalLink": "https://pubmed.ncbi.nlm.nih.gov/",
    "sourceName": "PubMed"
  }
]
